{
  "name": "[单位名称]",
  "status": "[企业运行状态]",
  "blockLevelName": "[网格级别]",
  "blockName": "[所属网格]",
  "longitude": "[x坐标]",
  "latitude": "[y坐标]",
  "address": "[单位地址]",
  "pollutantCode": "[污染源代码]",
  "zipCode": "[邮政编码]",
  "orgCode": "[组织机构代码]",
  "artificialPerson": "[法定代表人]",
  "apPosition": "[法定代表职务]",
  "apPhone": "[法定代表人电话]",
  "envPrincipal": "[环保负责人]",
  "epPosition": "[环保负责人职务]",
  "epPhone": "[环保负责人电话]",
  "pollutantType": "[污染源类型]",
  "pollutantLevel": "[污染源管理级别]",
  "superviseType": "[排污单位监管类型]",
  "isSpecial": "[是否特殊监管对象]",
  "registType": "[登记注册类型]",
  "registTime": "[登记注册时间]",
  "affiliation": "[隶属关系]",
  "scale": "[排污单位规模]",
  "industryType": "[行业类别]",
  "valley": "[所属流域]",
  "area": "[行政区]",
  "industrialPark": "[所在工业园区]",
  "openDate": "[开业时间]",
  "extensionDate": "[最近扩建时间]",
  "planeMap": "[平面图]",
  "attachmentId": "[附件id]",
  "orgInfo": "[单位介绍]",
  "envDesc": "[周边环境敏感点]"

}